{
  "family": "sentiment-analysis-task",
  "networkMode": "awsvpc",
  "requiresCompatibilities": ["FARGATE"],
  "cpu": "1024",
  "memory": "2048",
  "executionRoleArn": "arn:aws:iam::ACCOUNT_ID:role/ecsTaskExecutionRole",
  "taskRoleArn": "arn:aws:iam::ACCOUNT_ID:role/ecsTaskRole",
  "containerDefinitions": [
    {
      "name": "sentiment-analysis-app",
      "image": "ACCOUNT_ID.dkr.ecr.us-east-1.amazonaws.com/sentiment-analysis-app:latest",
      "portMappings": [
        {
          "containerPort": 8501,
          "protocol": "tcp"
        }
      ],
      "essential": true,
      "environment": [
        {
          "name": "AWS_DEFAULT_REGION",
          "value": "us-east-1"
        }
      ],
      "secrets": [
        {
          "name": "AWS_ACCESS_KEY_ID",
          "valueFrom": "arn:aws:secretsmanager:us-east-1:ACCOUNT_ID:secret:sentiment-analysis/aws-credentials:access-key-id::"
        },
        {
          "name": "AWS_SECRET_ACCESS_KEY",
          "valueFrom": "arn:aws:secretsmanager:us-east-1:ACCOUNT_ID:secret:sentiment-analysis/aws-credentials:secret-access-key::"
        }
      ],
      "logConfiguration": {
        "logDriver": "awslogs",
        "options": {
          "awslogs-group": "/ecs/sentiment-analysis",
          "awslogs-region": "us-east-1",
          "awslogs-stream-prefix": "ecs"
        }
      },
      "healthCheck": {
        "command": [
          "CMD-SHELL",
          "curl -f http://localhost:8501/_stcore/health || exit 1"
        ],
        "interval": 30,
        "timeout": 5,
        "retries": 3,
        "startPeriod": 60
      }
    }
  ]
}
